Metadata-Version: 2.1
Name: odoo14-addon-sale-financial-risk-info
Version: 14.0.1.1.0
Summary: Adds risk consumption info in sales orders.
Home-page: https://github.com/OCA/credit-control
Author: Tecnativa, Odoo Community Association (OCA)
Author-email: support@odoo-community.org
License: AGPL-3
Platform: UNKNOWN
Classifier: Programming Language :: Python
Classifier: Framework :: Odoo
Classifier: Framework :: Odoo :: 14.0
Classifier: License :: OSI Approved :: GNU Affero General Public License v3
Requires-Python: >=3.6
Requires-Dist: odoo14-addon-account-financial-risk
Requires-Dist: odoo (<14.1dev,>=14.0a)
